shapyro/__init__.py
shapyro/getobj.py
shapyro/op.py
shapyro/utils.py
shapyro-0.1.0.dist-info/LICENSE
shapyro-0.1.0.dist-info/METADATA
shapyro-0.1.0.dist-info/WHEEL
shapyro-0.1.0.dist-info/RECORD
