Metadata-Version: 2.1
Name: shapyro
Version: 0.1.0
Summary: Python-native data templating
License: MIT
Author: Zach Carlson
Author-email: fxchip+git@gmail.com
Requires-Python: >=3.10,<4.0
Classifier: License :: OSI Approved :: MIT License
Classifier: Programming Language :: Python :: 3
Classifier: Programming Language :: Python :: 3.10
Classifier: Programming Language :: Python :: 3.11
Classifier: Programming Language :: Python :: 3.12
